geosquare_grid/__init__.py
geosquare_grid/_version.py
geosquare_grid/core.py
geosquare_grid/utils.py
geosquare_grid-1.1.1.dist-info/licenses/LICENSE
geosquare_grid-1.1.1.dist-info/METADATA
geosquare_grid-1.1.1.dist-info/WHEEL
geosquare_grid-1.1.1.dist-info/top_level.txt
geosquare_grid-1.1.1.dist-info/RECORD
