Metadata-Version: 2.4
Name: geosquare-grid
Version: 1.1.1
Summary: A library for converting geographic coordinates to grid identifiers (GIDs) and performing spatial operations.
Home-page: https://github.com/geosquareai/geosquare-grid
Author: Geosquare Team
Author-email: Geosquare Team <admin@geosquare.ai>
License: GPL-3.0
Project-URL: Homepage, https://github.com/geosquareai/geosquare-grid
Project-URL: Repository, https://github.com/geosquareai/geosquare-grid
Keywords: geography,grid,coordinates,spatial,GIS
Classifier: Programming Language :: Python :: 3
Classifier: License :: OSI Approved :: GNU General Public License v3 (GPLv3)
Classifier: Operating System :: OS Independent
Requires-Python: >=3.7
License-File: LICENSE
Requires-Dist: shapely>=2.0.1
Provides-Extra: testing
Requires-Dist: pytest; extra == "testing"
Requires-Dist: pytest-cov; extra == "testing"
Dynamic: author
Dynamic: home-page
Dynamic: license-file
Dynamic: requires-python
